[
  {
    "CourseName": "--Select--"
  },
  {
    "CourseName": "Doctor of Medicine (D.M)"
  },
  {
    "CourseName": "Doctor of Philosophy (D.Phil)"
  },
  {
    "CourseName": "Doctor of Medicine (M.D)"
  },
  {
    "CourseName": "Doctor of Medicine in Ayurveda (M.D.Ayurveda)"
  },
  {
    "CourseName": "Doctor of Medicine in Homoeo (M.D.Homoeo)"
  },
  {
    "CourseName": "Doctor of Medicine in Siddha (M.D.Siddha)"
  },
  {
    "CourseName": "Doctor of Medicine in Unani (M.D.Unani)"
  },
  {
    "CourseName": "Doctor of Philosophy (Ph.D)"
  }
]